omero/plugins/__init__.py
omeroserver/__init__.py
omeroserver/version.py
omero_server-0.4.0.dist-info/LICENSE.txt
omero_server-0.4.0.dist-info/METADATA
omero_server-0.4.0.dist-info/WHEEL
omero_server-0.4.0.dist-info/top_level.txt
omero_server-0.4.0.dist-info/RECORD
